chat_plugin/__init__.py
chat_plugin/config.py
chat_plugin-0.1.2.dist-info/METADATA
chat_plugin-0.1.2.dist-info/WHEEL
chat_plugin-0.1.2.dist-info/licenses/LICENSE
chat_plugin-0.1.2.dist-info/RECORD
