Metadata-Version: 2.4
Name: chat_plugin
Version: 0.1.2
Summary: A NoneBot plugin for chatting with Ollama
Project-URL: Homepage, https://github.com/Ender-Kylin/Chat_Plugin
Project-URL: Repository, https://github.com/Ender-Kylin/Chat_Plugin.git
Project-URL: Issues, https://github.com/Ender-Kylin/Chat_Plugin/issues
Author-email: Your Name <your_email@example.com>
License: MIT License
License-File: LICENSE
Classifier: Development Status :: 3 - Alpha
Classifier: Intended Audience :: Developers
Classifier: License :: OSI Approved :: MIT License
Classifier: Programming Language :: Python :: 3
Classifier: Programming Language :: Python :: 3.8
Classifier: Programming Language :: Python :: 3.9
Classifier: Programming Language :: Python :: 3.10
Classifier: Programming Language :: Python :: 3.11
Classifier: Programming Language :: Python :: 3.12
Classifier: Topic :: Software Development :: Libraries :: Python Modules
Requires-Python: >=3.8
Requires-Dist: nonebot-adapter-onebot
Requires-Dist: nonebot2
Requires-Dist: ollama
Requires-Dist: pydantic
